{
  "fileName": "Electrical Engineer 10.pdf",
  "raw": "Sofia  Mehmeti  Personal Information  Gender Female Age 29 Nationality Albanian Location Munich, Germany  Summary Seasoned electrical technican with 6 years of experience in the automotive industry. Skilled in assembling, testing, and troubleshooting electrical components and systems. Proficient in interpreting technical drawings and specifications. Seeking to leverage practical experience and technical knowledge in a challenging engineering role.  Education  Bachelor’s degree in Electrical Engineering, TUM, Germany  Experience  Electrical Technician Hyundai Automotive Systems GmbH  Assembled and installed electrical components in vehicles, ensuring compliance with technical specifications and quality standards.  Conducted functional tests and diagnosed electrical issues to ensure optimal performance. February 2018 – Present (6 years) Munich, Germany  Skills   Proficient in electrical assembly and testing  Strong troubleshooting abilities  Ability to interpret technical drawings and specifications  Detail-oriented and quality-focused approach to work",
  "content": {
    "name": "Sofia Mehmeti",
    "role": "Electrical Engineer",
    "status": "active",
    "personal": {
      "Gender": "Female",
      "Age": "29",
      "Nationality": "Albanian",
      "Location": "Munich, Germany"
    },
    "education": [
      "Bachelor’s degree in Electrical Engineering,",
      "TUM, Germany"
    ],
    "experience": [
      {
        "position": "Electrical Technician",
        "company": "Hyundai Automotive Systems GmbH",
        "details": [
          "Assembled and installed electrical components in vehicles, ensuring compliance with technical",
          "specifications and quality standards.",
          "Conducted functional tests and diagnosed electrical issues to ensure optimal performance."
        ],
        "period": "February 2018 – Present (6 years)",
        "location": "Munich, Germany"
      }
    ],
    "skills": [
      "Proficient in electrical assembly and testing",
      "Strong troubleshooting abilities",
      "Ability to interpret technical drawings and specifications",
      "Detail-oriented and quality-focused approach to work"
    ]
  }
}