{
  "fileName": "IT Specialist 9.pdf",
  "raw": "Justin Davis  Personal Information  Gender Male Age 36 Nationality British Location Graz, Austria  Summary Dedicated professional with a background in sales and customer service, transitioning into the  field of IT infrastructure management. Strong problem-solving abilities and a keen interest in technology.  Eager to apply transferable skills and learn new technologies in a dynamic IT environment.  Education Bachelor's degree in Business Administration University of Edinburgh, UK  Experience IT Specialist TU Graz  Set up and administrate Jira and Confluence Systems  Provide technical support for IT-related issues. March 2023 – Present (1 year) Graz, Austria  Sales Representative Unicorn Corporation  Managed client accounts and promoted products/services to prospective customers.  Developed and maintained strong relationships with clients, ensuring customer  satisfaction and retention. March 2020 – January 2024 (4 years) Graz, Austria  Customer Service Manager ABC Services Ltd.  Led a team of customer service representatives, providing support and resolving customer issues.  Implemented strategies to improve customer satisfaction and streamline support processes. January 2018 – January 2020 (2 years) London, UK  Skills  Strong communication and interpersonal skills  Problem-solving and analytical abilities  Quick learner and adaptable to new technologies",
  "content": {
    "name": "Justin Davis",
    "role": "IT Infrastructure Specialist",
    "status": "active",
    "personal": {
      "Gender": "Male",
      "Age": "36",
      "Nationality": "British",
      "Location": "Graz, Austria"
    },
    "education": [
      "Bachelor's degree in Business Administration",
      "University of Edinburgh, UK"
    ],
    "experience": [
      {
        "position": "IT Specialist",
        "company": "TU Graz",
        "details": [
          "Set up and administrate Jira and Confluence Systems",
          "Provide technical support for IT-related issues."
        ],
        "period": "March 2023 – Present (1 year)",
        "location": "Graz, Austria"
      },
      {
        "position": "Sales Representative",
        "company": "Unicorn Corporation",
        "details": [
          "Managed client accounts and promoted products/services to prospective customers.",
          "Developed and maintained strong relationships with clients, ensuring customer",
          "satisfaction and retention."
        ],
        "period": "March 2020 – January 2024 (4 years)",
        "location": "Graz, Austria"
      },
      {
        "position": "Customer Service Manager",
        "company": "ABC Services Ltd.",
        "details": [
          "Led a team of customer service representatives, providing support and resolving customer issues.",
          "Implemented strategies to improve customer satisfaction and streamline support processes."
        ],
        "period": "January 2018 – January 2020 (2 years)",
        "location": "London, UK"
      }
    ],
    "skills": [
      "Strong communication and interpersonal skills",
      "Problem-solving and analytical abilities",
      "Quick learner and adaptable to new technologies"
    ]
  }
}