{
  "fileName": "Project Plant Engineer 9.pdf",
  "raw": "Tomas Schmidt  Personal Information  Gender Male Age 29 Nationality German Location Linz, Austria  Summary Driven engineer with a background in mechanical engineering. Graduated with a degree in mechanical engineering. Skilled in CAD design and technical drawing. Proficient in English and German.  Education  Bachelor's degree in Mechanical Engineering Linz University of Technology, Austria  Experience  CAD Technician ABC Engineering Firm  Created technical drawings and designs using CAD software.  Assisted in project documentation and coordination. September 2020 – Present (4 years) Linz, Austria  Languages English Fluent German Native",
  "content": {
    "name": "Tomas Schmidt",
    "role": "Project and Plant Engineer",
    "status": "active",
    "personal": {
      "Gender": "Male",
      "Age": "29",
      "Nationality": "German",
      "Location": "Linz, Austria"
    },
    "education": [
      "Bachelor's degree in Mechanical Engineering",
      "Linz University of Technology, Austria"
    ],
    "experience": [
      {
        "position": "CAD Technician",
        "company": "ABC Engineering Firm",
        "details": [
          "Created technical drawings and designs using CAD software.",
          "Assisted in project documentation and coordination."
        ],
        "period": "September 2020 – Present (4 years)",
        "location": "Linz, Austria"
      },
      {
        "position": "Languages:",
        "company": "German: Native"
      }
    ],
    "skills": []
  }
}