{
  "fileName": "SAP Consultant 11.pdf",
  "raw": "Bleona Likaj  Personal Information  Gender Female Age 28 Nationality Albanian Location Graz, Austria  Summary Dynamic and certified SAP consultant with 2 years of experience in SAP SD and MM modules. Completed relevant SAP certification courses. Skilled in analyzing business processes and providing effective SAP solutions. Strong customer service orientation and excellent communication skills.  Education  Bachelor's degree in Business Informatics Epoka University, Albania  Experience  SAP Consultant Cardo IT Solutions GmbH  Provided support and optimization for SAP SD and MM modules, ensuring smooth business operations.  Collaborated with clients to understand requirements and deliver tailored SAP solutions. June 2021 – Present (2 years) Graz, Austria  Certifications  SAP Certified Application Associate - SAP S/4 HANA Sales (C_TS460_1909) SAP Certified Application Associate - SAP S/4 HANA Procurement (C_TS450_1909)  Languages  English Fluent German Intermediate Albanian Native",
  "content": {
    "name": "Bleona Likaj",
    "role": "SAP Inhouse Consultant",
    "status": "active",
    "personal": {
      "Gender": "Female",
      "Age": "28",
      "Nationality": "Albanian",
      "Location": "Graz, Austria"
    },
    "education": [
      "Bachelor's degree in Business Informatics",
      "Epoka University, Albania"
    ],
    "experience": [
      {
        "position": "SAP Consultant",
        "company": "Cardo IT Solutions GmbH",
        "details": [
          "Provided support and optimization for SAP SD and MM modules, ensuring smooth business",
          "operations.",
          "Collaborated with clients to understand requirements and deliver tailored SAP solutions."
        ],
        "period": "June 2021 – Present (2 years)",
        "location": "Graz, Austria"
      },
      {
        "position": "Certifications:",
        "company": "Albanian: Native"
      }
    ],
    "skills": []
  }
}