{
  "fileName": "SAP Consultant 7.pdf",
  "raw": "Sarah Patel  Personal Information  Gender Female Age 30 Nationality Indian Location Graz, Austria  Summary Entry-level business administration graduate with a strong interest in SAP systems. Skilled in data analysis and process optimization. Completed relevant coursework in enterprise resource planning. Fluent in English and Hindi.  Education  Master's degree in Business Administration University of Graz, Austria  Experience  Business Analyst Intern Magna International, Graz   Assisted in analyzing business processes and requirements for system implementation.  Compiled reports and presentations for stakeholders. January 2023 – Present (1 year)  Languages  English Fluent Hindi Native",
  "content": {
    "name": "Sarah Patel",
    "role": "SAP Inhouse Consultant",
    "status": "active",
    "personal": {
      "Gender": "Female",
      "Age": "30",
      "Nationality": "Indian",
      "Location": "Graz, Austria"
    },
    "education": [
      "Master's degree in Business Administration",
      "University of Graz, Austria"
    ],
    "experience": [
      {
        "position": "Business Analyst Intern",
        "company": "Magna International, Graz",
        "details": [
          "Assisted in analyzing business processes and requirements for system implementation.",
          "Compiled reports and presentations for stakeholders."
        ],
        "period": "January 2023 – Present (1 year)",
        "location": "Languages:"
      },
      {
        "position": "English: Fluent",
        "company": "Hindi: Native"
      }
    ],
    "skills": []
  }
}