{
  "fileName": "System Lead 6.pdf",
  "raw": "L u c a s B r a m b e r g e r  Personal Information  Gender Male Age 36 Nationality Austrian Location Graz, Austria  Education  Bachelor's in Mechanical Engineering Vienna University of Technology, Austria  Experience  Mechanical Engineer Magna Manufacturing Company  Designed and developed mechanical systems for industrial applications.  Collaborated with cross-functional teams to integrate mechanical and electronic components. October 2017 – Present (6.5 years) Linz, Austria  IT Consultant GHI IT Solutions  Provided technical consulting services to clients on IT infrastructure and software solutions.  Developed expertise in cloud technologies and system integration. January 2015 – June 2017 (2.5 years) Vienna, Austria  Skills   Strong problem-solving and analytical skills from engineering background  Experience in IT consulting and system integration projects  Excellent communication and teamwork abilities  Proficient in English and German",
  "content": {
    "name": "LucasBramberger",
    "personal": {
      "Gender": "Male",
      "Age": "36",
      "Nationality": "Austrian",
      "Location": "Graz, Austria"
    },
    "education": [
      "Bachelor's in Mechanical Engineering",
      "Vienna University of Technology, Austria"
    ],
    "experience": [
      {
        "position": "Mechanical Engineer",
        "company": "Magna Manufacturing Company",
        "details": [
          "Designed and developed mechanical systems for industrial applications.",
          "Collaborated with cross-functional teams to integrate mechanical and electronic components."
        ],
        "period": "October 2017 – Present (6.5 years)",
        "location": "Linz, Austria"
      },
      {
        "position": "IT Consultant",
        "company": "GHI IT Solutions",
        "details": [
          "Provided technical consulting services to clients on IT infrastructure and software solutions.",
          "Developed expertise in cloud technologies and system integration."
        ],
        "period": "January 2015 – June 2017 (2.5 years)",
        "location": "Vienna, Austria"
      }
    ],
    "skills": [
      "Strong problem-solving and analytical skills from engineering background",
      "Experience in IT consulting and system integration projects",
      "Excellent communication and teamwork abilities",
      "Proficient in English and German"
    ]
  }
}