{
  "fileName": "Data Scientist 4.pdf",
  "raw": "H i r o s h i   T a n a k a  Personal Information  Gender Male Age 38 Nationality Japanese Location Japan, willing to relocate to Europe  Education  Master's in Statistics University of Tokyo, Japan  Experience  Data Scientist Daataa Financial Services  Developed predictive models for credit risk assessment and fraud detection using machine  learning techniques.  Analyzed financial data to identify market trends and develop investment strategies. January 2019 – Present (5 years) Tokyo, Japan  Researcher Graz University of Technology  Conducted research in computational statistics and machine learning, focusing on  algorithm development and optimization.  Published research papers in top-tier journals and presented findings at international conferences. January 2016 – January 2019 (3 years) Graz, Austria  Skills   Proficiency in Python and R for data analysis and modeling  Strong background in statistical theory and machine learning algorithms  Experience with big data technologies like Hadoop and Spark  Excellent problem-solving and analytical skills  Fluent in English, German and Japanese",
  "content": {
    "name": "HiroshiTanaka",
    "personal": {
      "Gender": "Male",
      "Age": "38",
      "Nationality": "Japanese",
      "Location": "Japan, willing to relocate to Europe"
    },
    "education": [
      "Master's in Statistics",
      "University of Tokyo, Japan"
    ],
    "experience": [
      {
        "position": "Data Scientist",
        "company": "Daataa Financial Services",
        "details": [
          "Developed predictive models for credit risk assessment and fraud detection using machine",
          "learning techniques.",
          "Analyzed financial data to identify market trends and develop investment strategies."
        ],
        "period": "January 2019 – Present (5 years)",
        "location": "Tokyo, Japan"
      },
      {
        "position": "Researcher",
        "company": "Graz University of Technology",
        "details": [
          "Conducted research in computational statistics and machine learning, focusing on",
          "algorithm development and optimization.",
          "Published research papers in top-tier journals and presented findings at international conferences."
        ],
        "period": "January 2016 – January 2019 (3 years)",
        "location": "Graz, Austria"
      }
    ],
    "skills": [
      "Proficiency in Python and R for data analysis and modeling",
      "Strong background in statistical theory and machine learning algorithms",
      "Experience with big data technologies like Hadoop and Spark",
      "Excellent problem-solving and analytical skills",
      "Fluent in English, German and Japanese"
    ]
  }
}