{
  "fileName": "Data Scientist 3.pdf",
  "raw": "Mi h i r   P a k i s t a n i  Personal Information  Gender Male Age 35 Nationality Pakistani Location Graz, Austria  Education  Master's in Mathematics Lahore University of Management Sciences, Pakistan  Experience  Data Scientist Drin Automotive Research Center  Developed predictive maintenance models for vehicle systems using machine learning algorithms.  Collaborated with engineers to optimize processes and improve operational efficiency based  on data insights. January 2020 – Present (4 years) Vienna, Austria  Business Intelligence Analyst ABC Corporation  Analyzed business performance data and generated actionable insights for decision-makers.  Developed data visualizations and interactive dashboards to track key performance indicators. September 2017 – January 2020 (2.5 years) Dubai  Skills   Strong proficiency in Python for data analysis and modeling  Experience with machine learning algorithms and statistical techniques  Excellent problem-solving and critical thinking abilities  Effective communication and presentation skills  Fluent in English, German and Urdu",
  "content": {
    "name": "MihirPakistani",
    "personal": {
      "Gender": "Male",
      "Age": "35",
      "Nationality": "Pakistani",
      "Location": "Graz, Austria"
    },
    "education": [
      "Master's in Mathematics",
      "Lahore University of Management Sciences, Pakistan"
    ],
    "experience": [
      {
        "position": "Data Scientist",
        "company": "Drin Automotive Research Center",
        "details": [
          "Developed predictive maintenance models for vehicle systems using machine learning algorithms.",
          "Collaborated with engineers to optimize processes and improve operational efficiency based",
          "on data insights."
        ],
        "period": "January 2020 – Present (4 years)",
        "location": "Vienna, Austria"
      },
      {
        "position": "Business Intelligence Analyst",
        "company": "ABC Corporation",
        "details": [
          "Analyzed business performance data and generated actionable insights for decision-makers.",
          "Developed data visualizations and interactive dashboards to track key performance indicators."
        ],
        "period": "September 2017 – January 2020 (2.5 years)",
        "location": "Dubai"
      }
    ],
    "skills": [
      "Strong proficiency in Python for data analysis and modeling",
      "Experience with machine learning algorithms and statistical techniques",
      "Excellent problem-solving and critical thinking abilities",
      "Effective communication and presentation skills",
      "Fluent in English, German and Urdu"
    ]
  }
}