{
  "fileName": "Electrical Engineer 8.pdf",
  "raw": "Anna Maria Sorento  Personal Information  Gender Female Age 33 Nationality Italian Location Vienna, Austria  Summary Seasoned electrical technician with a diverse background in industrial settings. Skilled in diagnosing and repairing electrical faults. Experienced in collaborating with engineering teams to implement system improvements. Eager to leverage practical experience in a challenging electrical engineering role. Fluent in English and Italian.  Education  Bachelor’s degree of Business Administration University of Padova Italy  Experience  Electrical Technician  Drita Industrial Solutions  Conducted routine maintenance and troubleshooting of electrical systems in manufacturing plants, ensuring uninterrupted production processes.  Collaborated with engineers to identify opportunities for system enhancements and efficiency improvements. March 2018 – Present (6 years) Lower Vienna, Austria  Languages  English Fluent German Intermediate Italian Native",
  "content": {
    "name": "Anna Maria Sorento",
    "role": "Electrical Engineer",
    "status": "active",
    "personal": {
      "Gender": "Female",
      "Age": "33",
      "Nationality": "Italian",
      "Location": "Vienna, Austria"
    },
    "education": [
      "Bachelor’s degree of Business Administration",
      "University of Padova Italy"
    ],
    "experience": [
      {
        "position": "Electrical Technician",
        "company": "Drita Industrial Solutions",
        "details": [
          "Conducted routine maintenance and troubleshooting of electrical systems in manufacturing plants,",
          "ensuring uninterrupted production processes.",
          "Collaborated with engineers to identify opportunities for system enhancements and efficiency",
          "improvements."
        ],
        "period": "March 2018 – Present (6 years)",
        "location": "Lower Vienna, Austria"
      },
      {
        "position": "Languages:",
        "company": "Italian: Native"
      }
    ],
    "skills": []
  }
}