{
  "fileName": "Program Manager 1.pdf",
  "raw": "Aleksandra Vucic  Personal Information  Gender Female Age 38 Nationality Serbian Location Serbia  Education  Master's in Mechanical Engineering University of Beograd, Serbia  Experience  Project Manager Me Automotive Company  Led vehicle integration projects from concept to series production.  Managed cross-functional teams and coordinated with customers to ensure project success. January 2018 – Present (6 years) Beograd, Serbia  Engineer ABC Motors  Worked on vehicle development projects, focusing on integration and testing.  Collaborated with suppliers and OEM partners to meet project requirements. January 2014 – January 2018 (4 years) Stuttgart, Germany  Skills   Extensive experience in vehicle development and integration projects  Strong leadership and communication skills  Proficient in project management methodologies  Familiarity with customer systems and processes in the automotive industry  Fluent in English, and German",
  "content": {
    "name": "Aleksandra Vucic",
    "role": "Program Manager",
    "status": "active",
    "personal": {
      "Gender": "Female",
      "Age": "38",
      "Nationality": "Serbian",
      "Location": "Serbia"
    },
    "education": [
      "Master's in Mechanical Engineering",
      "University of Beograd, Serbia"
    ],
    "experience": [
      {
        "position": "Project Manager",
        "company": "Me Automotive Company",
        "details": [
          "Led vehicle integration projects from concept to series production.",
          "Managed cross-functional teams and coordinated with customers to ensure project success."
        ],
        "period": "January 2018 – Present (6 years)",
        "location": "Beograd, Serbia"
      },
      {
        "position": "Engineer",
        "company": "ABC Motors",
        "details": [
          "Worked on vehicle development projects, focusing on integration and testing.",
          "Collaborated with suppliers and OEM partners to meet project requirements."
        ],
        "period": "January 2014 – January 2018 (4 years)",
        "location": "Stuttgart, Germany"
      }
    ],
    "skills": [
      "Extensive experience in vehicle development and integration projects",
      "Strong leadership and communication skills",
      "Proficient in project management methodologies",
      "Familiarity with customer systems and processes in the automotive industry",
      "Fluent in English, and German"
    ]
  }
}