{
  "fileName": "Project Plant Engineer 11.pdf",
  "raw": "Emily Fischer  Personal Information  Gender Female Age 33 Nationality Austrian Location Vienna, Austria  Summary Motivated and adaptable professional with a background in architecture transitioning into project and plant engineering. Possesses a strong foundation in design principles, technical drawing, and project management. Excels in problem-solving and collaboration. Eager to apply transferable skills to contribute to technically complex projects in the automotive industry.  Education Bachelor's degree in Architecture,  Vienna University of Technology, Austria  Master's degree in Architecture,  University of Applied Arts Vienna, Austria  Bachelor’s degree in Mechatronics  Ongoing  Experience Architectural Designer Brand Architecture Firm, Vienna (5 years)  Designed and managed construction projects, ensuring compliance with building codes and regulations.  Coordinated with clients, engineers, and contractors to deliver high-quality designs on schedule. April 2019 – Present (5 years) Vienna, Austria  Internship Construction Management Company  Assisted in project planning, budgeting, and scheduling.  Reviewed architectural plans and provided input on design modifications. January 2018 – January 2019 (1 year) Vienna, Austria  Languages  English Fluent German Native",
  "content": {
    "name": "Emily Fischer",
    "role": "Project and Plant Engineer",
    "status": "active",
    "personal": {
      "Gender": "Female",
      "Age": "33",
      "Nationality": "Austrian",
      "Location": "Vienna, Austria"
    },
    "education": [
      "Bachelor's degree in Architecture,",
      "Vienna University of Technology, Austria",
      "Master's degree in Architecture,",
      "University of Applied Arts Vienna, Austria",
      "Bachelor’s degree in Mechatronics",
      "Ongoing"
    ],
    "experience": [
      {
        "position": "Architectural Designer",
        "company": "Brand Architecture Firm, Vienna (5 years)",
        "details": [
          "Designed and managed construction projects, ensuring compliance with building codes and",
          "regulations.",
          "Coordinated with clients, engineers, and contractors to deliver high-quality designs on schedule."
        ],
        "period": "April 2019 – Present (5 years)",
        "location": "Vienna, Austria"
      },
      {
        "position": "Internship",
        "company": "Construction Management Company",
        "details": [
          "Assisted in project planning, budgeting, and scheduling.",
          "Reviewed architectural plans and provided input on design modifications."
        ],
        "period": "January 2018 – January 2019 (1 year)",
        "location": "Vienna, Austria"
      },
      {
        "position": "Languages:",
        "company": "German: Native"
      }
    ],
    "skills": []
  }
}