{
  "fileName": "Sales Manager 5.pdf",
  "raw": "Thomas Greiben  Personal Information  Gender Male Age 28 Nationality Austrian Location Graz, Austria  Education  Bachelor's degree in Mechanical Engineering University of Graz, Austria  Experience  Sales Trainee Motto Industrial Solutions  Assisted senior sales representatives in prospecting and lead generation activities.  Participated in sales meetings and training sessions to learn about sales techniques. January 2022 – Present (2 years) Graz, Austria  Intern XYZ Manufacturing GmbH  Assisted with market research and analysis to identify potential customers.  Provided administrative support to the sales team and helped organize sales events. June 2021 – January 2022 (6 months) Graz, Austria  Skills   Basic understanding of sales principles and techniques  Strong technical background in mechanical engineering  Excellent communication and interpersonal skills  Fluent in German and English",
  "content": {
    "name": "Thomas Greiben",
    "role": "Sales Manager",
    "status": "active",
    "personal": {
      "Gender": "Male",
      "Age": "28",
      "Nationality": "Austrian",
      "Location": "Graz, Austria"
    },
    "education": [
      "Bachelor's degree in Mechanical Engineering",
      "University of Graz, Austria"
    ],
    "experience": [
      {
        "position": "Sales Trainee",
        "company": "Motto Industrial Solutions",
        "details": [
          "Assisted senior sales representatives in prospecting and lead generation activities.",
          "Participated in sales meetings and training sessions to learn about sales techniques."
        ],
        "period": "January 2022 – Present (2 years)",
        "location": "Graz, Austria"
      },
      {
        "position": "Intern",
        "company": "XYZ Manufacturing GmbH",
        "details": [
          "Assisted with market research and analysis to identify potential customers.",
          "Provided administrative support to the sales team and helped organize sales events."
        ],
        "period": "June 2021 – January 2022 (6 months)",
        "location": "Graz, Austria"
      }
    ],
    "skills": [
      "Basic understanding of sales principles and techniques",
      "Strong technical background in mechanical engineering",
      "Excellent communication and interpersonal skills",
      "Fluent in German and English"
    ]
  }
}