{
  "fileName": "SAP Consultant 1.pdf",
  "raw": "Viktoria Ulz  Personal Information  Gender Female Age 36 Nationality Austrian Location Graz, Austria  Summary Experienced SAP consultant with a background in business administration. Skilled in SAP SD and MM modules with a focus on logistics processes. Solid experience in SAP customization and process optimization. Strong customer orientation and communication skills.  Education  Master's degree in Business Administration University of Graz, Austria  Bachelor's degree in Business Administration University of Graz, Austria   Experience  SAP Consultant Andi Consulting Services  Supported and optimized SAP SD and MM modules for various clients.  Led implementation and rollout projects, ensuring alignment with business requirements. June 2017 – Present (6 years) Graz, Austria  Business Analyst Intern Venture Corporation, Vienna   Assisted in analyzing and documenting business processes for system integration. January 2016 – April 2017 (1 year) Vienna, Austria  Languages  English Fluent German Fluent",
  "content": {
    "name": "Viktoria Ulz",
    "role": " SAP Inhouse Consultant",
    "status": "active",
    "personal": {
      "Gender": "Female",
      "Age": "36",
      "Nationality": "Austrian",
      "Location": "Graz, Austria"
    },
    "education": [
      "Master's degree in Business Administration",
      "University of Graz, Austria",
      "Bachelor's degree in Business Administration",
      "University of Graz, Austria"
    ],
    "experience": [
      {
        "position": "SAP Consultant",
        "company": "Andi Consulting Services",
        "details": [
          "Supported and optimized SAP SD and MM modules for various clients.",
          "Led implementation and rollout projects, ensuring alignment with business requirements."
        ],
        "period": "June 2017 – Present (6 years)",
        "location": "Graz, Austria"
      },
      {
        "position": "Business Analyst Intern",
        "company": "Venture Corporation, Vienna",
        "details": [
          "Assisted in analyzing and documenting business processes for system integration."
        ],
        "period": "January 2016 – April 2017 (1 year)",
        "location": "Vienna, Austria"
      },
      {
        "position": "Languages:",
        "company": "German: Fluent"
      }
    ],
    "skills": []
  }
}