{
  "fileName": "Security Manager 6.pdf",
  "raw": "Mira Rodriguez  Personal Information  Gender Female Age 26 Nationality Spanish Location Graz, Austria  Education  Bachelor's degree in Computer Engineering University of Barcelona, Spain  Certifications  Certified Information Systems Security Professional (CISSP) (in progress) CompTIA Security (in progress)  Experience  Junior IT Security Analyst ABC Solutions  Assisted in the management of IT systems and provided technical support to users.  Participated in projects related to IT infrastructure and cybersecurity. January 2023 – Present (1 year) Graz, Austria  Skills   Familiarity with ISO 27001 and GDPR concepts  Eagerness to learn and develop skills in information security  Analytical mindset and attention to detail  Fluent in Spanish and English  Willingness to learn German",
  "content": {
    "name": "Mira Rodriguez",
    "role": "Security Manager",
    "status": "active",
    "personal": {
      "Gender": "Female",
      "Age": "26",
      "Nationality": "Spanish",
      "Location": "Graz, Austria"
    },
    "education": [
      "Bachelor's degree in Computer Engineering",
      "University of Barcelona, Spain",
      "Certifications:",
      "Certified Information Systems Security Professional (CISSP) (in progress)",
      "CompTIA Security (in progress)"
    ],
    "experience": [
      {
        "position": "Junior IT Security Analyst",
        "company": "ABC Solutions",
        "details": [
          "Assisted in the management of IT systems and provided technical support to users.",
          "Participated in projects related to IT infrastructure and cybersecurity."
        ],
        "period": "January 2023 – Present (1 year)",
        "location": "Graz, Austria"
      }
    ],
    "skills": [
      "Familiarity with ISO 27001 and GDPR concepts",
      "Eagerness to learn and develop skills in information security",
      "Analytical mindset and attention to detail",
      "Fluent in Spanish and English",
      "Willingness to learn German"
    ]
  }
}