{
  "fileName": "Service Engineer 4.pdf",
  "raw": "Luca Rosi   Personal Information  Gender Male Age 27 Nationality Italian Location Graz, Austria  Summary Dynamic service engineer with a passion for analytical measuring systems. Graduated from a technical college with a specialization in mechatronic engineering. Skilled in maintenance, calibration, and troubleshooting. Highly adaptable with excellent problem-solving abilities.  Education  Diploma in Mechatronic Engineering Graz Technical University Graz, Austria  Experience  Service Technician GHI Instruments GmbH  Conducted service calls and maintenance of analytical measuring systems.  Assisted in troubleshooting activities. June 2022 – Present (1 year) Graz, Austria  Internship – Service Technician GHI Instruments GmbH January 2022 – June 2022 (6 months)  Languages  English Fluent German Fluent",
  "content": {
    "name": "LucaRosi",
    "role": "Service Engineer",
    "status": "active",
    "personal": {
      "Gender": "Male",
      "Age": "27",
      "Nationality": "Italian",
      "Location": "Graz, Austria"
    },
    "education": [
      "Diploma in Mechatronic Engineering",
      "Graz Technical University",
      "Graz, Austria"
    ],
    "experience": [
      {
        "position": "Service Technician",
        "company": "GHI Instruments GmbH",
        "details": [
          "Conducted service calls and maintenance of analytical measuring systems.",
          "Assisted in troubleshooting activities."
        ],
        "period": "June 2022 – Present (1 year)",
        "location": "Graz, Austria"
      },
      {
        "position": "Internship – Service Technician",
        "company": "German: Fluent"
      }
    ],
    "skills": []
  }
}