{
  "fileName": "System Lead 8.pdf",
  "raw": "Donald Fischer  Personal Information  Gender Male Age 34 Nationality German Location Munich, Germany  Education  Master's in Computer Science Technical University of Munich, Germany  Experience  System Architect System Software Solutions  Led the design and implementation of scalable and modular software architectures.  Collaborated with development teams to ensure architectural consistency and alignment  with business goals. April 2022 – Present (2 years) Munich, Germany  Solution Architect Cardo Tech Company  Developed architecture blueprints and roadmaps for enterprise solutions.  Provided technical guidance and support to project teams during implementation. January 2021 – January 2022 (1 year) Berlin, Germany  Enterprise Architect Cardo Consulting Group  Defined and maintained enterprise architecture frameworks and standards.  Conducted architecture reviews and provided recommendations for improvement. June 2017 – December 2020 (2.5 years) Hamburg, Germany  Skills   Proficient in enterprise architecture principles and practices  Experience in designing and implementing scalable software architectures  Strong analytical and problem-solving abilities  Excellent communication and collaboration skills  Fluent in English and German",
  "content": {
    "name": "Donald Fischer",
    "role": "Lead System & Enterprise Architect for Software Portfolio",
    "status": "active",
    "personal": {
      "Gender": "Male",
      "Age": "34",
      "Nationality": "German",
      "Location": "Munich, Germany"
    },
    "education": [
      "Master's in Computer Science",
      "Technical University of Munich, Germany"
    ],
    "experience": [
      {
        "position": "System Architect",
        "company": "System Software Solutions",
        "details": [
          "Led the design and implementation of scalable and modular software architectures.",
          "Collaborated with development teams to ensure architectural consistency and alignment",
          "with business goals."
        ],
        "period": "April 2022 – Present (2 years)",
        "location": "Munich, Germany"
      },
      {
        "position": "Solution Architect",
        "company": "Cardo Tech Company",
        "details": [
          "Developed architecture blueprints and roadmaps for enterprise solutions.",
          "Provided technical guidance and support to project teams during implementation."
        ],
        "period": "January 2021 – January 2022 (1 year)",
        "location": "Berlin, Germany"
      },
      {
        "position": "Enterprise Architect",
        "company": "Cardo Consulting Group",
        "details": [
          "Defined and maintained enterprise architecture frameworks and standards.",
          "Conducted architecture reviews and provided recommendations for improvement."
        ],
        "period": "June 2017 – December 2020 (2.5 years)",
        "location": "Hamburg, Germany"
      }
    ],
    "skills": [
      "Proficient in enterprise architecture principles and practices",
      "Experience in designing and implementing scalable software architectures",
      "Strong analytical and problem-solving abilities",
      "Excellent communication and collaboration skills",
      "Fluent in English and German"
    ]
  }
}