{
  "fileName": "Program Manager 6.pdf",
  "raw": "V i k t or i a H a r r i n g e r  Personal Information  Gender Female Age 32 Nationality Austrian Location Graz, Austria  Education  Dipl.-Ing. in Mechanical Engineering Graz University of Technology, Austria  Experience  Project Manager Magna International  Managed vehicle integration projects from concept to series production.  Led cross-functional teams and ensured compliance with project timelines and budgets. January 2019 – Present (5 years) Graz, Austria  Development Engineer Due Motors  Worked on vehicle testing and validation projects, focusing on integration and  performance optimization.  Collaborated with suppliers and internal teams to resolve technical issues and  improve product quality. June 2016 – January 2019 (2.5 years) Vienna, Austria  Skills  Experience in vehicle development and integration projects  Strong project management and leadership skills  Proficient in time and resource management  Excellent communication and interpersonal skills  Fluent in German and English",
  "content": {
    "name": "ViktoriaHarringer",
    "personal": {
      "Gender": "Female",
      "Age": "32",
      "Nationality": "Austrian",
      "Location": "Graz, Austria"
    },
    "education": [
      "Dipl.-Ing. in Mechanical Engineering",
      "Graz University of Technology, Austria"
    ],
    "experience": [
      {
        "position": "Project Manager",
        "company": "Magna International",
        "details": [
          "Managed vehicle integration projects from concept to series production.",
          "Led cross-functional teams and ensured compliance with project timelines and budgets."
        ],
        "period": "January 2019 – Present (5 years)",
        "location": "Graz, Austria"
      },
      {
        "position": "Development Engineer",
        "company": "Due Motors",
        "details": [
          "Worked on vehicle testing and validation projects, focusing on integration and",
          "performance optimization.",
          "Collaborated with suppliers and internal teams to resolve technical issues and",
          "improve product quality."
        ],
        "period": "June 2016 – January 2019 (2.5 years)",
        "location": "Vienna, Austria"
      }
    ],
    "skills": [
      "Experience in vehicle development and integration projects",
      "Strong project management and leadership skills",
      "Proficient in time and resource management",
      "Excellent communication and interpersonal skills",
      "Fluent in German and English"
    ]
  }
}