{
  "fileName": "Electrical Engineer 7.pdf",
  "raw": "D a n i e l D o u k a s  Personal Information  Gender Male Age 35 Nationality Greek Location Vienna, Austria  Summary Former industrial electrician with a successful transition into electrical engineering. Strong technical background combined with practical hands-on experience. Skilled in conceptualizing and designing electrical systems for industrial applications. Committed to continuous learning and professional development.  Education  Bachelor's degree in Electrical Engineering (part-time studies) Graz University of Technology, Austria  Experience  Industrial Electrician Biasim Manufacturing Company  Installed, maintained, and repaired electrical systems in an industrial setting, ensuring compliance with safety regulations.  Troubleshooted electrical issues and performed preventive maintenance tasks to minimize downtime. January 2016 – Present (8 years) Vienna, Austria  Electrical Engineer Trainee Dimitri Engineering Solutions GmbH  Completed a comprehensive training program in electrical engineering, gaining exposure to conceptualization and design of electrical systems.  Assisted senior engineers in project planning and execution. January 2014 – December 2015 (2 years) Athens, Greece  Languages  English Fluent German Fluent Greek Native",
  "content": {
    "name": "DanielDoukas",
    "personal": {
      "Gender": "Male",
      "Age": "35",
      "Nationality": "Greek",
      "Location": "Vienna, Austria"
    },
    "education": [
      "Bachelor's degree in Electrical Engineering (part-time studies)",
      "Graz University of Technology, Austria"
    ],
    "experience": [
      {
        "position": "Industrial Electrician",
        "company": "Biasim Manufacturing Company",
        "details": [
          "Installed, maintained, and repaired electrical systems in an industrial setting, ensuring",
          "compliance with safety regulations.",
          "Troubleshooted electrical issues and performed preventive maintenance tasks to minimize",
          "downtime."
        ],
        "period": "January 2016 – Present (8 years)",
        "location": "Vienna, Austria"
      },
      {
        "position": "Electrical Engineer Trainee",
        "company": "Dimitri Engineering Solutions GmbH",
        "details": [
          "Completed a comprehensive training program in electrical engineering, gaining exposure to",
          "conceptualization and design of electrical systems.",
          "Assisted senior engineers in project planning and execution."
        ],
        "period": "January 2014 – December 2015 (2 years)",
        "location": "Athens, Greece"
      },
      {
        "position": "Languages:",
        "company": "Greek: Native"
      }
    ],
    "skills": []
  }
}