{
  "fileName": "Electrical Engineer 3.pdf",
  "raw": "Moh a m mad Al  Personal Information  Gender Male Age 33 Nationality Palestine Location Graz, Austria  Summary Electrical engineer with a focus on technical sales and project work. Skilled in conceptual planning and detailed engineering of electrical systems for test systems. Experienced in collaborating with sales teams and managing supplier relationships. Fluent in English, Urdu, and German.  Education  Master’s degree in Electrical Engineering Graz University of Technology, Austria  Experience  Electrical Engineer Test Systems GmbH, Graz (6 years)  Contributed to the conceptual planning and detailed engineering of electrical systems for test systems, ensuring technical feasibility and cost-effectiveness.  Provided technical support to sales teams during customer interactions. March 2018 – Present (6 years) Graz, Austria  Languages  English Fluent German Fluent",
  "content": {
    "name": "MohammadAl",
    "personal": {
      "Gender": "Male",
      "Age": "33",
      "Nationality": "Palestine",
      "Location": "Graz, Austria"
    },
    "education": [
      "Master’s degree in Electrical Engineering",
      "Graz University of Technology, Austria"
    ],
    "experience": [
      {
        "position": "Electrical Engineer",
        "company": "Test Systems GmbH, Graz (6 years)",
        "details": [
          "Contributed to the conceptual planning and detailed engineering of electrical systems for test systems,",
          "ensuring technical feasibility and cost-effectiveness.",
          "Provided technical support to sales teams during customer interactions."
        ],
        "period": "March 2018 – Present (6 years)",
        "location": "Graz, Austria"
      },
      {
        "position": "Languages:",
        "company": "German: Fluent"
      }
    ],
    "skills": []
  }
}