{
  "fileName": "Project Plant Engineer 5.pdf",
  "raw": "F a t i m e   R a h m a n  Personal Information  Gender Female Age 50 Nationality Bangladeshi Location Vienna, Austria  Summary Motivated project engineer with a background in mechanical engineering. Graduated with a degree in plant engineering. Experienced in planning and design of technically complex projects. Strong analytical and communication skills. Fluent in English and Bengali.  Education  Bachelor's degree in Plant Engineering Vienna University of Applied Sciences  Austria  Experience  Project Engineer ABC Engineering Solutions,   Developed technical concepts and coordinated project activities.  Conducted direct communication with clients and suppliers. January 2020 – Present (4 years) Vienna, Austria  Plant Engineer Kuadrant Construction Solutions  In charge of technical planning and design of building projects. March 2005 – September 2019 (14 years) Bangladesh  Languages English Fluent Bengali Native",
  "content": {
    "name": "FatimeRahman",
    "personal": {
      "Gender": "Female",
      "Age": "50",
      "Nationality": "Bangladeshi",
      "Location": "Vienna, Austria"
    },
    "education": [
      "Bachelor's degree in Plant Engineering",
      "Vienna University of Applied Sciences",
      "Austria"
    ],
    "experience": [
      {
        "position": "Project Engineer",
        "company": "ABC Engineering Solutions,",
        "details": [
          "Developed technical concepts and coordinated project activities.",
          "Conducted direct communication with clients and suppliers."
        ],
        "period": "January 2020 – Present (4 years)",
        "location": "Vienna, Austria"
      },
      {
        "position": "Plant Engineer",
        "company": "Kuadrant Construction Solutions",
        "details": [
          "In charge of technical planning and design of building projects."
        ],
        "period": "March 2005 – September 2019 (14 years)",
        "location": "Bangladesh"
      },
      {
        "position": "Languages:",
        "company": "Bengali: Native"
      }
    ],
    "skills": []
  }
}