{
  "fileName": "Service Engineer 5.pdf",
  "raw": "S o p h i a   M u l l e r   Personal Information  Gender Female Age 33 Nationality Austrian Location Salzburg, Austria  Summary Results-oriented service engineer with a focus on analytical measuring systems. Graduated from a technical apprenticeship program in electrical engineering. Skilled in maintenance, calibration, and troubleshooting. Highly flexible with excellent communication skills.  Education  Apprenticeship in Electrical Engineering Technical School Salzburg Austria  Experience  Maintenance Engineer XYZ Analytical Solutions GmbH  Executed maintenance and calibration activities for analytical measuring systems.  Prepared service reports and protocols.  Internship – 1 year February 2019 – Present (5 years) Salzburg, Austria  Languages English Fluent German Fluent",
  "content": {
    "name": "SophiaMuller",
    "personal": {
      "Gender": "Female",
      "Age": "33",
      "Nationality": "Austrian",
      "Location": "Salzburg, Austria"
    },
    "education": [
      "Apprenticeship in Electrical Engineering",
      "Technical School Salzburg",
      "Austria"
    ],
    "experience": [
      {
        "position": "Maintenance Engineer",
        "company": "XYZ Analytical Solutions GmbH",
        "details": [
          "Executed maintenance and calibration activities for analytical measuring systems.",
          "Prepared service reports and protocols.",
          "Internship – 1 year"
        ],
        "period": "February 2019 – Present (5 years)",
        "location": "Salzburg, Austria"
      },
      {
        "position": "Languages:",
        "company": "German: Fluent"
      }
    ],
    "skills": []
  }
}