{
  "fileName": "Service Engineer 10.pdf",
  "raw": "S o f i a   P e t r o v a  Personal Information  Gender Female Age 28 Nationality Bulgarian Location Graz, Austria  Summary Energetic service engineer with a focus on analytical measuring systems. Graduated from a technical college with a specialization in mechatronic engineering. Skilled in maintenance, calibration, and troubleshooting. Highly adaptable with excellent communication skills.  Education  Diploma in Mechatronic Engineering American University of Bulgaria Bulgaria  Experience  Field Engineer XYZ Analytical Instruments GmbH  Conducted service calls and maintenance of analytical measuring systems.  Prepared service reports and documentation. March 2021 – Present (3 years) Graz, Austria  Technician ABC Tech Solutions  Provided technical support for electronic equipment.  Assisted in troubleshooting and repairs. January 2019 – January 2021 (2 years) Sofia, Bulgaria  Accounting Internship Sofia Municipality January 2018 – July 2018 (6 months) Sofia, Bulgaria  Languages English Fluent German Intermediate Bulgarian Native",
  "content": {
    "name": "SofiaPetrova",
    "personal": {
      "Gender": "Female",
      "Age": "28",
      "Nationality": "Bulgarian",
      "Location": "Graz, Austria"
    },
    "education": [
      "Diploma in Mechatronic Engineering",
      "American University of Bulgaria",
      "Bulgaria"
    ],
    "experience": [
      {
        "position": "Field Engineer",
        "company": "XYZ Analytical Instruments GmbH",
        "details": [
          "Conducted service calls and maintenance of analytical measuring systems.",
          "Prepared service reports and documentation."
        ],
        "period": "March 2021 – Present (3 years)",
        "location": "Graz, Austria"
      },
      {
        "position": "Technician",
        "company": "ABC Tech Solutions",
        "details": [
          "Provided technical support for electronic equipment.",
          "Assisted in troubleshooting and repairs."
        ],
        "period": "January 2019 – January 2021 (2 years)",
        "location": "Sofia, Bulgaria"
      },
      {
        "position": "Accounting Internship",
        "company": "Bulgarian: Native"
      }
    ],
    "skills": []
  }
}