{
  "fileName": "Service Engineer 6.pdf",
  "raw": "C h e n   W ei   Personal Information  Gender Male Age 36 Nationality Chinese Location Vienna, Austria  Summary Seasoned service engineer with a focus on analytical measuring systems. Graduated from a technical college in electrical engineering. Skilled in maintenance, calibration, and troubleshooting. Known for adaptability and effective communication skills.  Education  Diploma in Electrical Engineering Vienna University of Technology Vienna, Austria  Experience  Service Engineer ABC Analytical Instruments  Conducted service calls and maintenance of analytical measuring systems.  Prepared service reports and documentation. June 2021 – Present (2 years) Vienna, Austria  Technician XYZ Tech Solutions  Provided technical support and maintenance for various electronic systems.  Collaborated with engineers to develop troubleshooting strategies. January 2017 – January 2021 (4 years) Beijing, China   Languages  English Fluent German Intermediate Chinese Native",
  "content": {
    "name": "ChenWei",
    "personal": {
      "Gender": "Male",
      "Age": "36",
      "Nationality": "Chinese",
      "Location": "Vienna, Austria"
    },
    "education": [
      "Diploma in Electrical Engineering",
      "Vienna University of Technology",
      "Vienna, Austria"
    ],
    "experience": [
      {
        "position": "Service Engineer",
        "company": "ABC Analytical Instruments",
        "details": [
          "Conducted service calls and maintenance of analytical measuring systems.",
          "Prepared service reports and documentation."
        ],
        "period": "June 2021 – Present (2 years)",
        "location": "Vienna, Austria"
      },
      {
        "position": "Technician",
        "company": "XYZ Tech Solutions",
        "details": [
          "Provided technical support and maintenance for various electronic systems.",
          "Collaborated with engineers to develop troubleshooting strategies."
        ],
        "period": "January 2017 – January 2021 (4 years)",
        "location": "Beijing, China"
      },
      {
        "position": "Languages:",
        "company": "Chinese: Native"
      }
    ],
    "skills": []
  }
}